{
    "cli": {
        "version": ">= 5.0.0"
    },
    "build": {
        "development": {
            "developmentClient": true,
            "distribution": "internal",
            "android": {
                "buildType": "apk"
            },
            "ios": {
                "simulator": true
            },
            "env": {
                "EXPO_PUBLIC_USE_NGROK": "true",
                "EXPO_PUBLIC_NGROK_URL": "https://nonresilient-rylan-nondebilitating.ngrok-free.dev"
            }
        },
        "preview": {
            "distribution": "internal"
        },
        "production": {}
    }
}